setup.py
elastictrace/__init__.py
elastictrace/agent.py
elastictrace.egg-info/PKG-INFO
elastictrace.egg-info/SOURCES.txt
elastictrace.egg-info/dependency_links.txt
elastictrace.egg-info/entry_points.txt
elastictrace.egg-info/not-zip-safe
elastictrace.egg-info/requires.txt
elastictrace.egg-info/top_level.txt
elastictrace/lib/__init__.py
elastictrace/lib/cpu_stat.py
elastictrace/lib/disk_stat.py
elastictrace/lib/linux_metrics.py
elastictrace/lib/mem_stat.py
elastictrace/lib/net_stat.py
elastictrace/lib/proc_stat.py
elastictrace/lib/tail.py
elastictrace/lib/queuelib/__init__.py
elastictrace/lib/queuelib/pqueue.py
elastictrace/lib/queuelib/queue.py
elastictrace/plugin/__init__.py
elastictrace/plugin/apm.py
elastictrace/plugin/auth_log.py
elastictrace/plugin/base.py
elastictrace/plugin/helloworld.py
elastictrace/plugin/memcached.py
elastictrace/plugin/mongodb.py
elastictrace/plugin/mysql.py
elastictrace/plugin/netstat.py
elastictrace/plugin/nginx.py
elastictrace/plugin/ping.py
elastictrace/plugin/plugin.py
elastictrace/plugin/rethinkdb.py
elastictrace/plugin/system.py