Metadata-Version: 1.0
Name: elastictrace
Version: 0.4.7.3
Summary: elasticTrace Agent for getting server metrics upstream
Home-page: http://elastictrace.com/
Author: elasticTrace.com
Author-email: hello@elastictrace.com
License: UNKNOWN
Platform: UNKNOWN
